meliora/__init__.py
meliora/core.py
vangap_meliora1-0.0.1.dist-info/LICENSE
vangap_meliora1-0.0.1.dist-info/WHEEL
vangap_meliora1-0.0.1.dist-info/METADATA
vangap_meliora1-0.0.1.dist-info/RECORD
